easybert
